python_anticaptcha/__init__.py
python_anticaptcha/base.py
python_anticaptcha/compat.py
python_anticaptcha/exceptions.py
python_anticaptcha/tasks.py
python_anticaptcha-1.0.0.dist-info/LICENSE.md
python_anticaptcha-1.0.0.dist-info/METADATA
python_anticaptcha-1.0.0.dist-info/WHEEL
python_anticaptcha-1.0.0.dist-info/top_level.txt
python_anticaptcha-1.0.0.dist-info/RECORD
