Metadata-Version: 2.1
Name: python-anticaptcha
Version: 1.0.0
Summary: Client library for solve captchas with Anticaptcha.com support.
Home-page: https://github.com/ad-m/python-anticaptcha
Author: Adam Dobrawy
Author-email: anticaptcha@jawnosc.tk
License: MIT
Keywords: recaptcha captcha development
Platform: UNKNOWN
Classifier: Development Status :: 4 - Beta
Classifier: Intended Audience :: Developers
Classifier: License :: OSI Approved :: MIT License
Classifier: Programming Language :: Python :: 2
Classifier: Programming Language :: Python :: 2.7
Classifier: Programming Language :: Python :: 3
Classifier: Programming Language :: Python :: 3.4
Classifier: Programming Language :: Python :: 3.5
Classifier: Programming Language :: Python :: 3.6
Classifier: Programming Language :: Python :: 3.7
Classifier: Programming Language :: Python :: 3.8
Classifier: Programming Language :: Python :: 3.9
Classifier: Programming Language :: Python :: 3.10
Provides-Extra: tests
Provides-Extra: docs
